{"name":"build-javascript","namedChunkGroups":{"app":{"name":"app","assets":[{"name":"webpack-runtime-a9e457dbe48d1354071e.js","size":4068},{"name":"framework-6660ab3acb2349e32c56.js","size":141429},{"name":"styles.fccb3dd37b5d5968fb51.css","size":22848},{"name":"app-929250fdb005ed63fbd7.js","size":107317}],"filteredAssets":0,"assetsSize":275662,"filteredAuxiliaryAssets":3,"auxiliaryAssetsSize":726064},"component---src-pages-404-tsx":{"name":"component---src-pages-404-tsx","assets":[{"name":"framework-6660ab3acb2349e32c56.js","size":141429},{"name":"c16184b3-57cf46dd30b4128116a0.js","size":6258},{"name":"2cca2479-12f5c2d8008c711bf5cd.js","size":5741},{"name":"commons-e3e1bb7979d238e32f38.js","size":454841},{"name":"component---src-pages-404-tsx-87b8f45542ea67a45b31.js","size":1227}],"filteredAssets":0,"assetsSize":609496,"filteredAuxiliaryAssets":6,"auxiliaryAssetsSize":3929908},"component---src-pages-blog-tsx":{"name":"component---src-pages-blog-tsx","assets":[{"name":"framework-6660ab3acb2349e32c56.js","size":141429},{"name":"c16184b3-57cf46dd30b4128116a0.js","size":6258},{"name":"2cca2479-12f5c2d8008c711bf5cd.js","size":5741},{"name":"commons-e3e1bb7979d238e32f38.js","size":454841},{"name":"component---src-pages-blog-tsx-0446da42e8d1b663b2a7.js","size":9403}],"filteredAssets":0,"assetsSize":617672,"filteredAuxiliaryAssets":5,"auxiliaryAssetsSize":3821453},"component---src-pages-index-tsx":{"name":"component---src-pages-index-tsx","assets":[{"name":"framework-6660ab3acb2349e32c56.js","size":141429},{"name":"c16184b3-57cf46dd30b4128116a0.js","size":6258},{"name":"2cca2479-12f5c2d8008c711bf5cd.js","size":5741},{"name":"commons-e3e1bb7979d238e32f38.js","size":454841},{"name":"component---src-pages-index-tsx-474785053ec4c9ca5ebd.js","size":24251}],"filteredAssets":0,"assetsSize":632520,"filteredAuxiliaryAssets":7,"auxiliaryAssetsSize":4043356},"component---src-pages-model-generation-application-conditions-tsx":{"name":"component---src-pages-model-generation-application-conditions-tsx","assets":[{"name":"framework-6660ab3acb2349e32c56.js","size":141429},{"name":"c16184b3-57cf46dd30b4128116a0.js","size":6258},{"name":"2cca2479-12f5c2d8008c711bf5cd.js","size":5741},{"name":"commons-e3e1bb7979d238e32f38.js","size":454841},{"name":"fdb4b263a361d966ef65ed9496c0091929a2acbd-d1c56df02c92cd987848.js","size":15141},{"name":"component---src-pages-model-generation-application-conditions-tsx-a01aaa3fbf2fd1bd4f86.js","size":5242}],"filteredAssets":0,"assetsSize":628652,"filteredAuxiliaryAssets":8,"auxiliaryAssetsSize":4261284},"component---src-pages-model-generation-application-tsx":{"name":"component---src-pages-model-generation-application-tsx","assets":[{"name":"framework-6660ab3acb2349e32c56.js","size":141429},{"name":"c16184b3-57cf46dd30b4128116a0.js","size":6258},{"name":"2cca2479-12f5c2d8008c711bf5cd.js","size":5741},{"name":"commons-e3e1bb7979d238e32f38.js","size":454841},{"name":"fdb4b263a361d966ef65ed9496c0091929a2acbd-d1c56df02c92cd987848.js","size":15141}],"filteredAssets":0,"assetsSize":623410,"filteredAuxiliaryAssets":7,"auxiliaryAssetsSize":4251561},"component---src-pages-news-tsx":{"name":"component---src-pages-news-tsx","assets":[{"name":"framework-6660ab3acb2349e32c56.js","size":141429},{"name":"c16184b3-57cf46dd30b4128116a0.js","size":6258},{"name":"2cca2479-12f5c2d8008c711bf5cd.js","size":5741},{"name":"commons-e3e1bb7979d238e32f38.js","size":454841},{"name":"component---src-pages-news-tsx-38c2b7f8136fe8930808.js","size":9091}],"filteredAssets":0,"assetsSize":617360,"filteredAuxiliaryAssets":5,"auxiliaryAssetsSize":3819888}},"assetsByChunkName":{"app":["webpack-runtime-a9e457dbe48d1354071e.js","framework-6660ab3acb2349e32c56.js","styles.fccb3dd37b5d5968fb51.css","app-929250fdb005ed63fbd7.js"],"component---src-pages-404-tsx":["framework-6660ab3acb2349e32c56.js","c16184b3-57cf46dd30b4128116a0.js","2cca2479-12f5c2d8008c711bf5cd.js","commons-e3e1bb7979d238e32f38.js","component---src-pages-404-tsx-87b8f45542ea67a45b31.js"],"component---src-pages-blog-tsx":["framework-6660ab3acb2349e32c56.js","c16184b3-57cf46dd30b4128116a0.js","2cca2479-12f5c2d8008c711bf5cd.js","commons-e3e1bb7979d238e32f38.js","component---src-pages-blog-tsx-0446da42e8d1b663b2a7.js"],"component---src-pages-index-tsx":["framework-6660ab3acb2349e32c56.js","c16184b3-57cf46dd30b4128116a0.js","2cca2479-12f5c2d8008c711bf5cd.js","commons-e3e1bb7979d238e32f38.js","component---src-pages-index-tsx-474785053ec4c9ca5ebd.js"],"component---src-pages-model-generation-application-conditions-tsx":["framework-6660ab3acb2349e32c56.js","c16184b3-57cf46dd30b4128116a0.js","2cca2479-12f5c2d8008c711bf5cd.js","commons-e3e1bb7979d238e32f38.js","fdb4b263a361d966ef65ed9496c0091929a2acbd-d1c56df02c92cd987848.js","component---src-pages-model-generation-application-conditions-tsx-a01aaa3fbf2fd1bd4f86.js"],"component---src-pages-model-generation-application-tsx":["framework-6660ab3acb2349e32c56.js","c16184b3-57cf46dd30b4128116a0.js","2cca2479-12f5c2d8008c711bf5cd.js","commons-e3e1bb7979d238e32f38.js","fdb4b263a361d966ef65ed9496c0091929a2acbd-d1c56df02c92cd987848.js"],"component---src-pages-news-tsx":["framework-6660ab3acb2349e32c56.js","c16184b3-57cf46dd30b4128116a0.js","2cca2479-12f5c2d8008c711bf5cd.js","commons-e3e1bb7979d238e32f38.js","component---src-pages-news-tsx-38c2b7f8136fe8930808.js"]},"childAssetsByChunkName":{}}